pygametools/__init__.py
pygametools/elements.py
pygametools/props.py
pygametools/view3d/__init__.py
pygametools/view3d/classes.py
pygametools/view3d/matcaps.py
pygametools-0.0.2.dist-info/LICENSE
pygametools-0.0.2.dist-info/METADATA
pygametools-0.0.2.dist-info/WHEEL
pygametools-0.0.2.dist-info/top_level.txt
pygametools-0.0.2.dist-info/RECORD
